{
  "posts": [
    {
      "title": "Added",
      "stared": true,
      "opened": false,
      "backgroundColor": "green",
      "lists": [
        {
          "name": "Added",
          "cards": []
        },
        {
          "name": "added2",
          "cards": []
        },
        {
          "name": "added3",
          "cards": []
        }
      ],
      "id": 2
    },
    {
      "title": "Added 2",
      "stared": true,
      "opened": false,
      "backgroundColor": "violet",
      "lists": [
        {
          "name": "Added 2",
          "cards": []
        }
      ],
      "id": 3
    },
    {
      "title": "tts",
      "stared": true,
      "opened": false,
      "backgroundColor": "cyan",
      "lists": [],
      "id": 4
    }
  ],
  "colors": [
    "red",
    "green",
    "white",
    "pink",
    "violet",
    "lightgray",
    "cyan"
  ]
}